{
  "Knives Out": "/backdrops/546554-backdrop.jpg",
  "Wake Up Dead Man: A Knives Out Mystery": "/backdrops/812583-backdrop.jpg",
  "Mamma Mia!": "/backdrops/11631-backdrop.jpg",
  "Harry Potter and the Deathly Hallows Part 2": "/backdrops/12445-backdrop.jpg",
  "Harry Potter and the Deathly Hallows Part 1": "/backdrops/12444-backdrop.jpg",
  "Harry Potter and the Half-Blood Prince": "/backdrops/767-backdrop.jpg",
  "Harry Potter and the Order of the Phoenix": "/backdrops/675-backdrop.jpg",
  "Harry Potter and the Goblet of Fire": "/backdrops/674-backdrop.jpg",
  "Harry Potter and the Prisoner of Azkaban": "/backdrops/673-backdrop.jpg",
  "Harry Potter and the Chamber of Secrets": "/backdrops/672-backdrop.jpg",
  "Harry Potter and the Sorcerer's Stone": "/backdrops/671-backdrop.jpg",
  "F1": "/backdrops/911430-backdrop.jpg",
  "The Incredibles": "/backdrops/9806-backdrop.jpg",
  "Dinosaur": "/backdrops/10567-backdrop.jpg",
  "Toy Story": "/backdrops/862-backdrop.jpg",
  "The Rainmaker": "/backdrops/11975-backdrop.jpg",
  "Blood Diamond": "/backdrops/1372-backdrop.jpg",
  "The Pink Panther": "/backdrops/12096-backdrop.jpg",
  "Ray": "/backdrops/1677-backdrop.jpg",
  "Fantasia": "/backdrops/756-backdrop.jpg",
  "X-Men Origins: Wolverine": "/backdrops/2080-backdrop.jpg",
  "The Cat Returns": "/backdrops/15370-backdrop.jpg",
  "Spirited Away": "/backdrops/129-backdrop.jpg",
  "Speed Racer": "/backdrops/7459-backdrop.jpg",
  "Robots": "/backdrops/9928-backdrop.jpg",
  "Hero": "/backdrops/51550-backdrop.jpg",
  "Mr. Bean's Holiday": "/backdrops/1268-backdrop.jpg",
  "The Hunger Games: The Ballad of Songbirds and Snakes": "/backdrops/695721-backdrop.jpg",
  "Death at a Funeral": "/backdrops/2196-backdrop.jpg",
  "Undercover Brother": "/backdrops/12277-backdrop.jpg",
  "Fantastic Beasts and Where to Find Them": "/backdrops/259316-backdrop.jpg",
  "Back to the Future": "/backdrops/105-backdrop.jpg",
  "Casino Royale": "/backdrops/12208-backdrop.jpg",
  "Star Trek Beyond": "/backdrops/188927-backdrop.jpg",
  "Star Trek Into Darkness": "/backdrops/54138-backdrop.jpg",
  "Guardians of the Galaxy": "/backdrops/118340-backdrop.jpg",
  "Sinbad: Legend of the Seven Seas": "/backdrops/14411-backdrop.jpg",
  "Star Wars: Episode VI - Return of the Jedi": "/backdrops/1892-backdrop.jpg",
  "Star Wars: Episode V - The Empire Strikes Back": "/backdrops/1891-backdrop.jpg",
  "Star Wars: Episode III - Revenge of the Sith": "/backdrops/1895-backdrop.jpg",
  "Star Wars: Episode II - Attack of the Clones": "/backdrops/1894-backdrop.jpg",
  "Star Wars: Episode I - The Phantom Menace": "/backdrops/1893-backdrop.jpg",
  "Ted Lasso": "/backdrops/97546-backdrop.jpg",
  "The Bear": "/backdrops/136315-backdrop.jpg",
  "Abbott Elementary": "/backdrops/125935-backdrop.jpg",
  "The Grand Budapest Hotel": "/backdrops/120467-backdrop.jpg",
  "Severance": "/backdrops/95396-backdrop.jpg",
  "Avatar: The Last Airbender": "/backdrops/246-backdrop.jpg",
  "Paddington 2": "/backdrops/346648-backdrop.jpg"
}
